Metadata-Version: 2.1
Name: pano-airflow-providers-amazon
Version: 8.0.0
Summary: Provider for Apache Airflow. Implements apache-airflow-providers-amazon package
Home-page: https://airflow.apache.org/
Download-URL: https://archive.apache.org/dist/airflow/providers
Author: Apache Software Foundation
Author-email: dev@airflow.apache.org
License: Apache License 2.0
Project-URL: Documentation, https://airflow.apache.org/docs/apache-airflow-providers-amazon/8.0.0/
Project-URL: Bug Tracker, https://github.com/apache/airflow/issues
Project-URL: Source Code, https://github.com/apache/airflow
Project-URL: Slack Chat, https://s.apache.org/airflow-slack
Project-URL: Twitter, https://twitter.com/ApacheAirflow
Project-URL: YouTube, https://www.youtube.com/channel/UCSXwxpWZQ7XZ1WL3wqevChA/
Classifier: Development Status :: 5 - Production/Stable
Classifier: Environment :: Console
Classifier: Environment :: Web Environment
Classifier: Intended Audience :: Developers
Classifier: Intended Audience :: System Administrators
Classifier: Framework :: Apache Airflow
Classifier: Framework :: Apache Airflow :: Provider
Classifier: License :: OSI Approved :: Apache Software License
Classifier: Programming Language :: Python :: 3.7
Classifier: Programming Language :: Python :: 3.8
Classifier: Programming Language :: Python :: 3.9
Classifier: Programming Language :: Python :: 3.10
Classifier: Topic :: System :: Monitoring
Requires-Python: ~=3.7
License-File: LICENSE
License-File: NOTICE
Requires-Dist: apache-airflow-providers-common-sql (>=1.3.1)
Requires-Dist: apache-airflow (>=2.3.0)
Requires-Dist: asgiref
Requires-Dist: boto3 (>=1.24.0)
Requires-Dist: jsonpath-ng (>=1.5.3)
Requires-Dist: mypy-boto3-appflow (>=1.24.0)
Requires-Dist: mypy-boto3-rds (>=1.24.0)
Requires-Dist: mypy-boto3-redshift-data (>=1.24.0)
Requires-Dist: redshift-connector (>=2.0.888)
Requires-Dist: sqlalchemy-redshift (>=0.8.6)
Requires-Dist: watchtower (~=2.0.1)
Provides-Extra: aiobotocore
Requires-Dist: aiobotocore[boto3] (>=2.2.0) ; extra == 'aiobotocore'
Provides-Extra: apache.hive
Requires-Dist: apache-airflow-providers-apache-hive ; extra == 'apache.hive'
Provides-Extra: cncf.kubernetes
Requires-Dist: apache-airflow-providers-cncf-kubernetes ; extra == 'cncf.kubernetes'
Provides-Extra: common.sql
Requires-Dist: apache-airflow-providers-common-sql ; extra == 'common.sql'
Provides-Extra: exasol
Requires-Dist: apache-airflow-providers-exasol ; extra == 'exasol'
Provides-Extra: ftp
Requires-Dist: apache-airflow-providers-ftp ; extra == 'ftp'
Provides-Extra: google
Requires-Dist: apache-airflow-providers-google ; extra == 'google'
Provides-Extra: imap
Requires-Dist: apache-airflow-providers-imap ; extra == 'imap'
Provides-Extra: mongo
Requires-Dist: apache-airflow-providers-mongo ; extra == 'mongo'
Provides-Extra: pandas
Requires-Dist: pandas (>=0.17.1) ; extra == 'pandas'
Provides-Extra: salesforce
Requires-Dist: apache-airflow-providers-salesforce ; extra == 'salesforce'
Provides-Extra: ssh
Requires-Dist: apache-airflow-providers-ssh ; extra == 'ssh'
